{
    "deckbuilder": {
        "addButtons": [1,2,3],
        "columns": [
            {"propName": "name", "label": "id:name"},
            {"propName": "type", "label": "id:type"},
            {"propName": "subType", "label": "id:subType"}
        ],
        "spawnGroups": [
            {"loadGroupId": "playerNinPlay", "label": "id:myPlayArea"},
            {"loadGroupId": "playerNDeck", "label": "id:myDeck"},
            {"loadGroupId": "player1inPlay", "label": "id:player1inPlay"},
            {"loadGroupId": "player1Deck", "label": "id:player1Deck"},
            {"loadGroupId": "player2inPlay", "label": "id:player2inPlay"},
            {"loadGroupId": "player2Deck", "label": "id:player2Deck"},
            {"loadGroupId": "sharedStoryDeck", "label": "id:sharedStoryDeck"}
        ]
    }
}